cythereal_cli/__init__.py
cythereal_cli/api_client.py
cythereal_cli/cli.py
cythereal_cli/upload.py
cythereal_cli/util/__init__.py
cythereal_cli/util/hashing.py
cythereal_magic/__init__.py
cythereal_magic/api_client.py
cythereal_magic/configuration.py
cythereal_magic/rest.py
cythereal_magic/api/__init__.py
cythereal_magic/api/files_api.py
cythereal_magic/api/genomics_api.py
cythereal_magic/api/groups_api.py
cythereal_magic/api/indicators_api.py
cythereal_magic/api/procedures_api.py
cythereal_magic/api/reports_api.py
cythereal_magic/api/search_api.py
cythereal_magic/api/support_api.py
cythereal_magic/api/tags_api.py
cythereal_magic/api/users_api.py
cythereal_magic/api/yara_api.py
cythereal_magic/models/__init__.py
cythereal_magic/models/all_of_direct_reputation_reputation.py
cythereal_magic/models/all_of_file_avscan.py
cythereal_magic/models/all_of_file_campaign.py
cythereal_magic/models/all_of_file_categories.py
cythereal_magic/models/all_of_file_child_avscan.py
cythereal_magic/models/all_of_file_child_campaign.py
cythereal_magic/models/all_of_file_child_categories.py
cythereal_magic/models/all_of_file_child_families.py
cythereal_magic/models/all_of_file_child_labels.py
cythereal_magic/models/all_of_file_child_matches.py
cythereal_magic/models/all_of_file_child_notes.py
cythereal_magic/models/all_of_file_child_pipeline.py
cythereal_magic/models/all_of_file_child_reputation.py
cythereal_magic/models/all_of_file_child_unmapped.py
cythereal_magic/models/all_of_file_children.py
cythereal_magic/models/all_of_file_families.py
cythereal_magic/models/all_of_file_labels.py
cythereal_magic/models/all_of_file_match_response_avscan.py
cythereal_magic/models/all_of_file_match_response_campaign.py
cythereal_magic/models/all_of_file_match_response_categories.py
cythereal_magic/models/all_of_file_match_response_children.py
cythereal_magic/models/all_of_file_match_response_families.py
cythereal_magic/models/all_of_file_match_response_labels.py
cythereal_magic-2.0.5.dist-info/METADATA
cythereal_magic-2.0.5.dist-info/WHEEL
cythereal_magic-2.0.5.dist-info/entry_points.txt
cythereal_magic-2.0.5.dist-info/top_level.txt
cythereal_magic-2.0.5.dist-info/RECORD
