Metadata-Version: 2.1
Name: cythereal-magic
Version: 2.0.5
Summary: MAGIC™ API
Home-page: 
Author-email: support@unknowncyber.com
Keywords: Swagger,MAGIC™ API
Requires-Dist: urllib3 >=1.15
Requires-Dist: six >=1.10
Requires-Dist: certifi
Requires-Dist: python-dateutil
Requires-Dist: click >=6.7
